LICENSE
benchling_cli/__init__.py
benchling_cli/__main__.py
benchling_cli/apps/__init__.py
benchling_cli/apps/cli.py
benchling_cli/apps/codegen/__init__.py
benchling_cli/apps/codegen/generate_dependencies_module.py
benchling_cli/apps/codegen/generate_models.py
benchling_cli/apps/codegen/helpers.py
benchling_cli/apps/codegen/templates/dependencies.py.jinja2
benchling_cli/apps/codegen/templates/dropdown_model.py.jinja2
benchling_cli/apps/codegen/templates/enum_scalar_model.py.jinja2
benchling_cli/apps/codegen/templates/schema_instance_model.py.jinja2
benchling_cli/apps/codegen/templates/workflow_instance_model.py.jinja2
benchling_cli/cli.py
benchling_cli/py.typed
benchling_cli-0.8.3a0.dist-info/entry_points.txt
benchling_cli-0.8.3a0.dist-info/LICENSE
benchling_cli-0.8.3a0.dist-info/WHEEL
benchling_cli-0.8.3a0.dist-info/METADATA
benchling_cli-0.8.3a0.dist-info/RECORD
