Metadata-Version: 2.1
Name: benchling-cli
Version: 0.8.3a0
Summary: CLI for assistance in developing with the Benchling Platform.
License: Apache-2.0
Author: Benchling Support
Author-email: support@benchling.com
Requires-Python: >=3.8,<4.0
Classifier: License :: OSI Approved :: Apache Software License
Classifier: Programming Language :: Python :: 3
Classifier: Programming Language :: Python :: 3.8
Classifier: Programming Language :: Python :: 3.9
Classifier: Programming Language :: Python :: 3.10
Classifier: Programming Language :: Python :: 3.11
Requires-Dist: Jinja2 (>=3.1.2,<4.0.0)
Requires-Dist: autoflake (>=1.7,<2.0)
Requires-Dist: benchling_sdk (>=1.8.0,<2.0.0)
Requires-Dist: black (>=22.3.0,<23.0.0)
Requires-Dist: typer (>=0.6.1,<0.7.0)
